polling2.py
polling2-0.4.7.dist-info/LICENSE.md
polling2-0.4.7.dist-info/METADATA
polling2-0.4.7.dist-info/WHEEL
polling2-0.4.7.dist-info/top_level.txt
polling2-0.4.7.dist-info/RECORD
