Metadata-Version: 2.1
Name: polling2
Version: 0.4.7
Summary: Updated polling utility with many configurable options
Home-page: http://github.com/ddmee/polling2
Author: Donal Mee
Author-email: mee.donal@gmail.com
License: UNKNOWN
Platform: UNKNOWN
Classifier: Programming Language :: Python :: 2
Classifier: Programming Language :: Python :: 3
Classifier: License :: OSI Approved :: MIT License
Classifier: Operating System :: OS Independent
License-File: LICENSE.md
